ktimeout/__init__.py
ktimeout/timeout.py
ktimeout-0.0.7.dist-info/LICENSE
ktimeout-0.0.7.dist-info/METADATA
ktimeout-0.0.7.dist-info/WHEEL
ktimeout-0.0.7.dist-info/top_level.txt
ktimeout-0.0.7.dist-info/RECORD
