Metadata-Version: 2.1
Name: ktimeout
Version: 0.0.7
Summary: add timeout to any function
Home-page: https://github.com/kkristof200/py_timeout
Author: Kristof
License: UNKNOWN
Platform: UNKNOWN
Classifier: Programming Language :: Python :: 3
Classifier: License :: OSI Approved :: MIT License
Classifier: Operating System :: OS Independent
Requires-Python: >=3.5
